ml/__init__.py
ml/datasets.py
ml/pc.py
ml/schedulers.py
ml/train.py
ml/utils.py
ml/models/__init__.py
ml/models/common.py
ml/models/rnns/__init__.py
ml/models/rnns/rnns.py
ml/models/transformers/__init__.py
ml/models/transformers/attention.py
ml/models/transformers/transformers.py
m24842_ml-1.5.36.dist-info/METADATA
m24842_ml-1.5.36.dist-info/WHEEL
m24842_ml-1.5.36.dist-info/top_level.txt
m24842_ml-1.5.36.dist-info/RECORD
