Metadata-Version: 2.4
Name: m24842_ml
Version: 1.5.36
Summary: Collection of ML models and benchmarking tools
Requires-Python: >=3.8
Requires-Dist: torch
Requires-Dist: torchdiffeq
Requires-Dist: torchvision
Requires-Dist: transformers
Requires-Dist: datasets==3.6.0
Requires-Dist: tensor_parallel
Requires-Dist: numpy
Requires-Dist: pandas
Requires-Dist: einops
Requires-Dist: opt_einsum
Requires-Dist: rotary_embedding_torch
Requires-Dist: wandb
Requires-Dist: pyyaml
Requires-Dist: tqdm
Requires-Dist: zstandard
Provides-Extra: cuda
Requires-Dist: mamba-ssm; extra == "cuda"
Requires-Dist: causal-conv1d; extra == "cuda"
